xasdesvid/__init__.py
xasdesvid/connection.py
xasdesvid-0.2.dist-info/METADATA
xasdesvid-0.2.dist-info/WHEEL
xasdesvid-0.2.dist-info/top_level.txt
xasdesvid-0.2.dist-info/RECORD
