Metadata-Version: 2.1
Name: xasdesvid
Version: 0.2
Summary: Библиотека для определения вида связи в словосочетаниях.
Home-page: https://github.com/XasdesST/xasdesvid
Author: XasdesNew
Author-email: nikakovnikak574@gmail.com
Requires-Dist: pymorphy2
